eta_optimize/__init__.py
eta_optimize-0.1.0.dist-info/LICENSE
eta_optimize-0.1.0.dist-info/METADATA
eta_optimize-0.1.0.dist-info/WHEEL
eta_optimize-0.1.0.dist-info/RECORD
